MANIFEST.in
README.md
setup.py
src/vdk/plugin/server/configmap-local-registry-hosting-template.yaml
src/vdk/plugin/server/ingress-nginx-deploy.yaml
src/vdk/plugin/server/installer.py
src/vdk/plugin/server/kind-cluster-config-template.yaml
src/vdk/plugin/server/server_plugin.py
src/vdk/plugin/server/server_plugin_utils.py
src/vdk_server.egg-info/PKG-INFO
src/vdk_server.egg-info/SOURCES.txt
src/vdk_server.egg-info/dependency_links.txt
src/vdk_server.egg-info/entry_points.txt
src/vdk_server.egg-info/requires.txt
src/vdk_server.egg-info/top_level.txt
tests/test_plugin_template.py